octo_aws_common/__init__.py
octo_aws_common/api_gateway_application.py
octo_aws_common/batch_application.py
octo_aws_common/dynamo_streams_application.py
octo_aws_common/lambda_application.py
octo_aws_common/sns_application.py
octo_aws_common/sqs_application.py
octo_aws_common-0.1.6.dist-info/WHEEL
octo_aws_common-0.1.6.dist-info/METADATA
octo_aws_common-0.1.6.dist-info/RECORD
