Metadata-Version: 2.1
Name: octo-aws-common
Version: 0.1.6
Summary: 
Author: Your Name
Author-email: you@example.com
Requires-Python: >=3.8,<4.0
Classifier: Programming Language :: Python :: 3
Classifier: Programming Language :: Python :: 3.8
Classifier: Programming Language :: Python :: 3.9
Requires-Dist: aws-lambda-powertools (>=1.21.1,<2.0.0)
Requires-Dist: boto3 (>=1.19.7,<2.0.0)
